concentration/__init__.py
concentration/output.py
concentration/run.py
concentration/settings.py
concentration-1.1.5.dist-info/entry_points.txt
concentration-1.1.5.dist-info/LICENSE
concentration-1.1.5.dist-info/WHEEL
concentration-1.1.5.dist-info/METADATA
concentration-1.1.5.dist-info/RECORD
