Metadata-Version: 2.1
Name: concentration
Version: 1.1.5
Summary: Get work done when you need to, goof off when you don't.
License: MIT
Author: Timothy Crosley
Author-email: timothy.crosley@gmail.com
Requires-Python: >=3.6,<4.0
Classifier: License :: OSI Approved :: MIT License
Classifier: Programming Language :: Python :: 3
Classifier: Programming Language :: Python :: 3.6
Classifier: Programming Language :: Python :: 3.7
Classifier: Programming Language :: Python :: 3.8
Classifier: Programming Language :: Python :: 3.9
Requires-Dist: hug (>=2.6.1,<3.0.0)
